[
  {
    "dataHoraId": "2023-12-01T19:30:00",
    "idCongregacao": 1,
    "cultoDeSantaCeia": false,
    "dataHoraCulto": "01/12 sexta 19:30",
    "obreiroPonto1": "Aline",
    "obreiroPonto2": "-",
    "obreiroPonto3": "Hudson - Luiz",
    "obreiroOferta": "Alanês - Ronaldo Moital"
  },
  {
    "dataHoraId": "2023-12-03T10:00:00",
    "idCongregacao": 1,
    "cultoDeSantaCeia": true,
    "dataHoraCulto": "03/12 domingo 10:00",
    "obreiroPonto1": "Cilene",
    "obreiroPonto2": "Fabio - Isaias Manoel",
    "obreiroPonto3": "Luiz - Tiago",
    "obreiroOferta": "Isaias Manoel - Fabio - Lucimar - Janice"
  },
  {
    "dataHoraId": "2023-12-03T18:30:00",
    "idCongregacao": 1,
    "cultoDeSantaCeia": false,
    "dataHoraCulto": "03/12 domingo 18:30",
    "obreiroPonto1": "Izaias Santos",
    "obreiroPonto2": "Ronaldo Martins - Éder",
    "obreiroPonto3": "Edivan - Izaias Santos",
    "obreiroOferta": "Ronaldo Martins - Gisele - Nathascha - Éder"
  },
  {
    "dataHoraId": "2023-12-06T19:30:00",
    "idCongregacao": 1,
    "cultoDeSantaCeia": false,
    "dataHoraCulto": "06/12 quarta 19:30",
    "obreiroPonto1": "Edivan",
    "obreiroPonto2": "-",
    "obreiroPonto3": "Samer - Lucas",
    "obreiroOferta": "Hudson - Ronaldo Moital"
  },
  {
    "dataHoraId": "2023-12-08T19:30:00",
    "idCongregacao": 1,
    "cultoDeSantaCeia": false,
    "dataHoraCulto": "08/12 sexta 19:30",
    "obreiroPonto1": "Samer",
    "obreiroPonto2": "-",
    "obreiroPonto3": "Isaias Manoel - Alanês",
    "obreiroOferta": "Lucas - Fabio"
  },
  {
    "dataHoraId": "2023-12-10T18:30:00",
    "idCongregacao": 1,
    "cultoDeSantaCeia": false,
    "dataHoraCulto": "10/12 domingo 18:30",
    "obreiroPonto1": "Isaias Manoel",
    "obreiroPonto2": "Samer - Isaias Pereira",
    "obreiroPonto3": "Ronaldo Moital - Tiago",
    "obreiroOferta": "Samer - Ronaldo Martins - Isaias Pereira - Éder"
  },
  {
    "dataHoraId": "2023-12-13T19:30:00",
    "idCongregacao": 1,
    "cultoDeSantaCeia": false,
    "dataHoraCulto": "13/12 quarta 19:30",
    "obreiroPonto1": "Tiago",
    "obreiroPonto2": "-",
    "obreiroPonto3": "Edivan - Izaias Santos",
    "obreiroOferta": "Nathascha - Luiz"
  },
  {
    "dataHoraId": "2023-12-15T19:30:00",
    "idCongregacao": 1,
    "cultoDeSantaCeia": false,
    "dataHoraCulto": "15/12 sexta 19:30",
    "obreiroPonto1": "Ronaldo Martins",
    "obreiroPonto2": "-",
    "obreiroPonto3": "Hudson - Isaias Manoel",
    "obreiroOferta": "Aline - Janice"
  },
  {
    "dataHoraId": "2023-12-17T18:30:00",
    "idCongregacao": 1,
    "cultoDeSantaCeia": false,
    "dataHoraCulto": "17/12 domingo 18:30",
    "obreiroPonto1": "Ronaldo Moital",
    "obreiroPonto2": "Isaias Pereira - Alanês",
    "obreiroPonto3": "Fabio - Tiago",
    "obreiroOferta": "Lucas - Isaias Pereira - Alanês - Lucimar"
  },
  {
    "dataHoraId": "2023-12-20T19:30:00",
    "idCongregacao": 1,
    "cultoDeSantaCeia": false,
    "dataHoraCulto": "20/12 quarta 19:30",
    "obreiroPonto1": "Alanês",
    "obreiroPonto2": "-",
    "obreiroPonto3": "Ronaldo Moital - Samer",
    "obreiroOferta": "Nathascha - Gisele"
  },
  {
    "dataHoraId": "2023-12-22T19:30:00",
    "idCongregacao": 1,
    "cultoDeSantaCeia": false,
    "dataHoraCulto": "22/12 sexta 19:30",
    "obreiroPonto1": "Luiz",
    "obreiroPonto2": "-",
    "obreiroPonto3": "Ronaldo Martins - Éder",
    "obreiroOferta": "Aline - Isaias Pereira"
  },
  {
    "dataHoraId": "2023-12-24T18:30:00",
    "idCongregacao": 1,
    "cultoDeSantaCeia": false,
    "dataHoraCulto": "24/12 domingo 18:30",
    "obreiroPonto1": "Éder",
    "obreiroPonto2": "Izaias Santos - Edivan",
    "obreiroPonto3": "Isaias Manoel - Luiz",
    "obreiroOferta": "Izaias Santos - Edivan - Hudson - Alanês"
  },
  {
    "dataHoraId": "2023-12-27T19:30:00",
    "idCongregacao": 1,
    "cultoDeSantaCeia": false,
    "dataHoraCulto": "27/12 quarta 19:30",
    "obreiroPonto1": "Tiago",
    "obreiroPonto2": "-",
    "obreiroPonto3": "Éder - Lucas",
    "obreiroOferta": "Samer - Ronaldo Martins"
  },
  {
    "dataHoraId": "2023-12-29T19:30:00",
    "idCongregacao": 1,
    "cultoDeSantaCeia": false,
    "dataHoraCulto": "29/12 sexta 19:30",
    "obreiroPonto1": "Edivan",
    "obreiroPonto2": "-",
    "obreiroPonto3": "Luiz - Fabio",
    "obreiroOferta": "Janice - Mary"
  },
  {
    "dataHoraId": "2023-12-31T18:30:00",
    "idCongregacao": 1,
    "cultoDeSantaCeia": false,
    "dataHoraCulto": "31/12 domingo 18:30",
    "obreiroPonto1": "Fabio",
    "obreiroPonto2": "Ronaldo Moital - Izaias Santos",
    "obreiroPonto3": "Tiago - Edivan",
    "obreiroOferta": "Izaias Santos - Aline - Isaias Manoel - Ronaldo Moital"
  }
]